neoagent/__init__.py
neoagent/module.py
neoflow-0.0.1.dist-info/LICENSE
neoflow-0.0.1.dist-info/METADATA
neoflow-0.0.1.dist-info/WHEEL
neoflow-0.0.1.dist-info/top_level.txt
neoflow-0.0.1.dist-info/RECORD
