Metadata-Version: 2.1
Name: neoflow
Version: 0.0.1
Summary: A Python package for build angent.
Author-email: YiShen <shenyibox@gmail.com>
License: 
Project-URL: Homepage, https://github.com/yourusername/neoagent
Project-URL: Repository, https://github.com/yourusername/neoagent
Classifier: Programming Language :: Python :: 3
Classifier: License :: OSI Approved :: MIT License
Classifier: Operating System :: OS Independent
Requires-Python: >=3.8
License-File: LICENSE
